flask_admin_lite/__init__.py
flask_admin_lite/base.py
flask_admin_lite/model_view.py
flask_admin_lite/utils.py
flask_admin_lite-0.1.0.dist-info/DESCRIPTION.rst
flask_admin_lite-0.1.0.dist-info/METADATA
flask_admin_lite-0.1.0.dist-info/RECORD
flask_admin_lite-0.1.0.dist-info/WHEEL
flask_admin_lite-0.1.0.dist-info/metadata.json
flask_admin_lite-0.1.0.dist-info/top_level.txt
