Metadata-Version: 2.0
Name: flask-admin-lite
Version: 0.1.0
Summary: Build lightweight admin panel for your models
Home-page: https://github.com/wong2/flask-admin-lite
Author: wong2
Author-email: wonderfuly@gmail.com
License: MIT
Platform: UNKNOWN
Requires-Dist: flask-paginate
Requires-Dist: flask-wtf
